cli_tracker/__init__.py
cli_tracker/integrations/__init__.py
cli_tracker/integrations/atexit.py
cli_tracker/sdk.py
cli_tracker-0.3.5.dist-info/LICENSE
cli_tracker-0.3.5.dist-info/METADATA
cli_tracker-0.3.5.dist-info/WHEEL
cli_tracker-0.3.5.dist-info/RECORD
