Metadata-Version: 2.1
Name: cli_tracker
Version: 0.3.5
Summary: 
Home-page: https://gefyra.dev
Keywords: CLI
Author: Robert Stein
Author-email: robert@blueshoe.de
Requires-Python: >=3.8,<4.0
Classifier: Intended Audience :: Developers
Classifier: Operating System :: MacOS
Classifier: Operating System :: POSIX :: Linux
Classifier: Programming Language :: Python :: 3
Classifier: Programming Language :: Python :: 3.8
Classifier: Programming Language :: Python :: 3.9
Classifier: Programming Language :: Python :: 3.10
Classifier: Programming Language :: Python :: 3.11
Classifier: Programming Language :: Python :: 3.12
Classifier: Programming Language :: Python :: 3.13
Classifier: Topic :: Software Development :: Build Tools
Requires-Dist: distro (>=1.7.0,<2.0.0) ; sys_platform == "linux"
Requires-Dist: sentry-sdk (>=2.17.0,<3.0.0)
Project-URL: Documentation, https://gefyra.dev
Project-URL: Repository, https://github.com/gefyrahq/cli_tracker/
